grep_ast/__init__.py
grep_ast/dump.py
grep_ast/grep_ast.py
grep_ast/main.py
grep_ast/parsers.py
grep_ast/tsl.py
grep_ast-0.8.0.dist-info/LICENSE.txt
grep_ast-0.8.0.dist-info/METADATA
grep_ast-0.8.0.dist-info/WHEEL
grep_ast-0.8.0.dist-info/entry_points.txt
grep_ast-0.8.0.dist-info/top_level.txt
grep_ast-0.8.0.dist-info/RECORD
