Metadata-Version: 2.2
Name: grep-ast
Version: 0.8.0
Summary: A tool to grep through the AST of a source file
Home-page: https://github.com/paul-gauthier/grep-ast
Classifier: License :: OSI Approved :: Apache Software License
License-File: LICENSE.txt
Requires-Dist: tree-sitter-language-pack
Requires-Dist: pathspec
Dynamic: classifier
Dynamic: description
Dynamic: description-content-type
Dynamic: home-page
Dynamic: requires-dist
Dynamic: summary
